neuralsampler/__init__.py
neuralsampler/networks.py
neuralsampler/neural_sampler.py
neuralsampler/utils.py
neuralsampler/datasets/__init__.py
neuralsampler/datasets/gen_data.py
neuralsampler/datasets/gen_uniform.py
neuralsampler/datasets/load_data.py
neuralsampler/divergence/__init__.py
neuralsampler/divergence/mmd.py
neuralsampler/mcmc/__init__.py
neuralsampler/mcmc/langevin.py
neuralsampler/physys/__init__.py
neuralsampler/physys/dw.py
neuralsampler/physys/gaussian.py
neuralsampler/physys/mb.py
neuralsampler/vis/__init__.py
neuralsampler/vis/anim.py
neuralsampler-0.0.16.dist-info/LICENSE
neuralsampler-0.0.16.dist-info/METADATA
neuralsampler-0.0.16.dist-info/WHEEL
neuralsampler-0.0.16.dist-info/top_level.txt
neuralsampler-0.0.16.dist-info/RECORD
