Metadata-Version: 2.1
Name: neuralsampler
Version: 0.0.16
Summary: neural sampler
Home-page: https://github.com/JiahaoYao/neuralsampler
Author: Jimmy
Author-email: jiahaoyao.math@gmail.com
License: MIT
Keywords: artificial intelligence,generative models,transformers
Platform: UNKNOWN
Classifier: Development Status :: 4 - Beta
Classifier: Intended Audience :: Developers
Classifier: Topic :: Scientific/Engineering :: Artificial Intelligence
Classifier: License :: OSI Approved :: MIT License
Classifier: Programming Language :: Python :: 3.6
Requires-Dist: gdown
Requires-Dist: torch (>=1.6)
Requires-Dist: sysflow
Requires-Dist: wandb
Requires-Dist: tqdm (==4.59.0)
Requires-Dist: celluloid
Requires-Dist: mediapy
